file_merger/__init__.py
file_merger/helper.py
file_merger/main.py
file_merger-0.1.0rc2.dist-info/entry_points.txt
file_merger-0.1.0rc2.dist-info/WHEEL
file_merger-0.1.0rc2.dist-info/METADATA
file_merger-0.1.0rc2.dist-info/RECORD
