Metadata-Version: 2.1
Name: file-merger
Version: 0.1.0rc2
Summary: Merge multiple text files into one
Home-page: https://github.com/istudyatuni/file-merger
Author: Ilia
Author-email: istudyatuni@gmail.com
Requires-Python: >=3.6,<4.0
Classifier: Programming Language :: Python :: 3
Classifier: Programming Language :: Python :: 3.10
Classifier: Programming Language :: Python :: 3.6
Classifier: Programming Language :: Python :: 3.7
Classifier: Programming Language :: Python :: 3.8
Classifier: Programming Language :: Python :: 3.9
Requires-Dist: PyYAML (>=6.0,<7.0)
Project-URL: Repository, https://github.com/istudyatuni/file-merger
Project-URL: Tracker, https://github.com/istudyatuni/file-merger/issues
